citrine/__init__.py
citrine/ast.py
citrine/citrine.py
citrine/core.py
citrine/elements.py
citrine/parser.py
mandarin/__init__.py
mandarin/ast.py
mandarin/core.py
mandarin/elements.py
mandarin/parser.py
mandarin-0.0.1a2.dist-info/LICENSE
mandarin-0.0.1a2.dist-info/METADATA
mandarin-0.0.1a2.dist-info/WHEEL
mandarin-0.0.1a2.dist-info/top_level.txt
mandarin-0.0.1a2.dist-info/RECORD
