Metadata-Version: 2.1
Name: mandarin
Version: 0.0.1a2
Summary: Template engine for Python
Home-page: https://github.com/joegasewicz/password-mixin
Author: Joe Gasewicz
Author-email: joegasewicz@gmail.com
License: UNKNOWN
Platform: UNKNOWN
Classifier: Programming Language :: Python :: 3.0
Classifier: Programming Language :: Python :: 3.9
Classifier: License :: OSI Approved :: GNU General Public License v3 or later (GPLv3+)
Classifier: Operating System :: OS Independent
License-File: LICENSE
